magentic_one_cli/__init__.py
magentic_one_cli/__main__.py
magentic_one_cli/_m1.py
magentic_one_cli/py.typed
magentic_one_cli-0.2.4.dist-info/METADATA
magentic_one_cli-0.2.4.dist-info/WHEEL
magentic_one_cli-0.2.4.dist-info/entry_points.txt
magentic_one_cli-0.2.4.dist-info/licenses/LICENSE-CODE
magentic_one_cli-0.2.4.dist-info/RECORD
