Metadata-Version: 2.4
Name: magentic-one-cli
Version: 0.2.4
Summary: Magentic-One is a generalist multi-agent system, built on `AutoGen-AgentChat`, for solving complex web and file-based tasks. This package installs the `m1` command-line utility to quickly get started with Magentic-One.
License:     MIT License
License-File: LICENSE-CODE
Classifier: License :: OSI Approved :: MIT License
Classifier: Operating System :: OS Independent
Classifier: Programming Language :: Python :: 3
Requires-Python: >=3.10
Requires-Dist: autogen-agentchat<0.5,>=0.4.4
Requires-Dist: autogen-ext[docker,magentic-one,openai,rich]<0.5,>=0.4.4
Requires-Dist: pyyaml>=5.1
